cloud_storage_provider/__init__.py
cloud_storage_provider/constants.py
cloud_storage_provider/utils.py
cloud_storage_provider/base/__init__.py
cloud_storage_provider/base/csp.py
cloud_storage_provider/dropbox_csp/__init__.py
cloud_storage_provider/dropbox_csp/dropbox_cloud_storage_provider.py
cloud_storage_provider/ibm/__init__.py
cloud_storage_provider/ibm/constants.py
cloud_storage_provider/ibm/ibm_cloud_storage_provider.py
cloud_storage_provider/ibm/injector_utils.py
dropbox_csp-1.0.2.dist-info/LICENSE
dropbox_csp-1.0.2.dist-info/METADATA
dropbox_csp-1.0.2.dist-info/WHEEL
dropbox_csp-1.0.2.dist-info/top_level.txt
dropbox_csp-1.0.2.dist-info/RECORD
