Metadata-Version: 2.1
Name: dropbox-csp
Version: 1.0.2
Summary: Dropbox wrapper client to upload data files to a folder
Home-page: UNKNOWN
Author: EddyMM
Author-email: mwendaeddy@gmail.com
License: UNKNOWN
Platform: UNKNOWN
Classifier: Programming Language :: Python :: 3
Classifier: License :: OSI Approved :: MIT License
Classifier: Operating System :: OS Independent
Requires-Dist: backcall (==0.1.0)
Requires-Dist: certifi (==2019.6.16)
Requires-Dist: chardet (==3.0.4)
Requires-Dist: decorator (==4.4.0)
Requires-Dist: dropbox (==9.4.0)
Requires-Dist: idna (==2.8)
Requires-Dist: ipython (==7.6.1)
Requires-Dist: ipython-genutils (==0.2.0)
Requires-Dist: jedi (==0.14.1)
Requires-Dist: parso (==0.5.1)
Requires-Dist: pexpect (==4.7.0)
Requires-Dist: pickleshare (==0.7.5)
Requires-Dist: prompt-toolkit (==2.0.9)
Requires-Dist: ptyprocess (==0.6.0)
Requires-Dist: Pygments (==2.4.2)
Requires-Dist: requests (==2.22.0)
Requires-Dist: six (==1.12.0)
Requires-Dist: traitlets (==4.3.2)
Requires-Dist: urllib3 (==1.25.3)
Requires-Dist: wcwidth (==0.1.7)
